llamazure/tresource/__init__.py
llamazure/tresource/itresource.py
llamazure/tresource/mp.py
llamazure/tresource/tresource.py
llamazure.tresource-0.1.0.dist-info/METADATA
llamazure.tresource-0.1.0.dist-info/WHEEL
llamazure.tresource-0.1.0.dist-info/namespace_packages.txt
llamazure.tresource-0.1.0.dist-info/top_level.txt
llamazure.tresource-0.1.0.dist-info/RECORD
