Metadata-Version: 2.1
Name: llamazure.tresource
Version: 0.1.0
Summary: Group Azure resources into their hierarchy
Author: Daniel Goldman
License: Round Robin 2.0.0
Classifier: Development Status :: 3 - Alpha
Classifier: Programming Language :: Python :: 3.9
Classifier: Programming Language :: Python :: 3.10
Classifier: Programming Language :: Python :: 3.11
Classifier: Programming Language :: Python :: 3.12
Classifier: Programming Language :: Python :: 3.13
Classifier: Topic :: Utilities
Classifier: Topic :: Internet :: Log Analysis
Requires-Python: >=3.9
Requires-Dist: llamazure.rid (~=0.1.0)
